[
    {
        "id": "MLfG3-sErfU",
        "title": "Connecting to the Well Connect"
    },
    {
        "id": "VnGrfOhmHrQ",
        "title": "Linking a Fixture"
    },
    {
        "id": "F_I-teQIHgI",
        "title": "Unlink Fixtures"
    },
    {
        "id": "ZpIGfQeIsoI",
        "title": "Add Fixture / Patch Fixture "
      },
      {
        "id": "vnXPfBsJFGU",
        "title": "Add Fixtures to Plot"
      },
      {
        "id": "utlQQ8VvVJA",
        "title": "Creating a Grouping and Groups"
      },
      {
        "id": "OkTeXIHIWRE",
        "title": "step 5"
      },
      {
        "id": "miJKGeziARE",
        "title": "step 6"
      },
      {
        "id": "rHZ9b_WcTT8",
        "title": "step 7"
      }
]
